AUTHORS
MANIFEST.in
README.rst
setup.py
OceanMonkey.egg-info/PKG-INFO
OceanMonkey.egg-info/SOURCES.txt
OceanMonkey.egg-info/dependency_links.txt
OceanMonkey.egg-info/entry_points.txt
OceanMonkey.egg-info/not-zip-safe
OceanMonkey.egg-info/requires.txt
OceanMonkey.egg-info/top_level.txt
oceanmonkey/VERSION
oceanmonkey/__init__.py
oceanmonkey/__main__.py
oceanmonkey/cmdline.py
oceanmonkey/exceptions.py
oceanmonkey/commands/__init__.py
oceanmonkey/commands/run.py
oceanmonkey/commands/startproject.py
oceanmonkey/core/__init__.py
oceanmonkey/core/database.py
oceanmonkey/core/engine.py
oceanmonkey/core/filters.py
oceanmonkey/core/monkey.py
oceanmonkey/core/queue.py
oceanmonkey/core/request.py
oceanmonkey/core/response.py
oceanmonkey/core/signal.py
oceanmonkey/core/template.py
oceanmonkey/settings/__init__.py
oceanmonkey/settings/default_settings.py
oceanmonkey/templates/monkeys/__init__.py
oceanmonkey/templates/monkeys/gibbons.py.tmpl
oceanmonkey/templates/monkeys/orangutans.py.tmpl
oceanmonkey/templates/project/oceanmonkey.cfg
oceanmonkey/templates/project/module/__init__.py
oceanmonkey/templates/project/module/middlewares.py.tmpl
oceanmonkey/templates/project/module/settings.py.tmpl
oceanmonkey/utils/__init__.py
oceanmonkey/utils/bye.py
oceanmonkey/utils/commands.py
oceanmonkey/utils/log.py
oceanmonkey/utils/queues.py
oceanmonkey/utils/url.py
oceanmonkey/utils/settings/__init__.py
oceanmonkey/utils/settings/concurrency.py
oceanmonkey/utils/settings/deploy.py
oceanmonkey/utils/settings/filters.py
oceanmonkey/utils/settings/headers.py
oceanmonkey/utils/settings/middleware.py
oceanmonkey/utils/settings/monkey.py
oceanmonkey/utils/settings/queue.py
oceanmonkey/utils/settings/seeds.py
oceanmonkey/utils/settings/source.py
oceanmonkey/utils/settings/time.py